setup.py
pdf/__init__.py
pdf/modify/__init__.py
pdf/modify/_version.py
pdf/modify/canvas/__init__.py
pdf/modify/canvas/constructor.py
pdf/modify/canvas/objects.py
pdf/modify/draw/__init__.py
pdf/modify/draw/pdf.py
pdfconduit/__init__.py
pdfconduit_modify.egg-info/PKG-INFO
pdfconduit_modify.egg-info/SOURCES.txt
pdfconduit_modify.egg-info/dependency_links.txt
pdfconduit_modify.egg-info/namespace_packages.txt
pdfconduit_modify.egg-info/requires.txt
pdfconduit_modify.egg-info/top_level.txt